[
    {
      "ПОЗИЦИЈА": 1,
      "ТИМ": "БЕСА 1976",
      "ИЗИГРАНИ": 15,
      "ПОБЕДЕНИ": 13,
      "НЕРЕШЕНИ": 1,
      "ИЗГУБЕНИ": 1,
      "ГОЛОВИДП": "37:8",
      "ГОЛРАЗЛИКА": 29,
      "ПОЕНИ": 40
    },
    {
      "ПОЗИЦИЈА": 2,  
      "ТИМ": "ДЕТОНИТ ПЛАЧКОВИЦА",
      "ИЗИГРАНИ": 15,
      "ПОБЕДЕНИ": 11,
      "НЕРЕШЕНИ": 2,
      "ИЗГУБЕНИ": 2,
      "ГОЛОВИДП": "28:8",
      "ГОЛРАЗЛИКА": 20,
      "ПОЕНИ": 35
    },
    {
      "ПОЗИЦИЈА": 3,  
      "ТИМ": "ПЕЛИСТЕР",
      "ИЗИГРАНИ": 15,
      "ПОБЕДЕНИ": 10,
      "НЕРЕШЕНИ": 3,
      "ИЗГУБЕНИ": 2,
      "ГОЛОВИДП": "30:9",
      "ГОЛРАЗЛИКА": 21,
      "ПОЕНИ": 33
    },
    {
      "ПОЗИЦИЈА": 4,  
      "ТИМ": "АРСИМИ",
      "ИЗИГРАНИ": 15,
      "ПОБЕДЕНИ": 7,
      "НЕРЕШЕНИ": 2,
      "ИЗГУБЕНИ": 6,
      "ГОЛОВИДП": "27:15",
      "ГОЛРАЗЛИКА": 12,
      "ПОЕНИ": 23
    },
    {
      "ПОЗИЦИЈА": 5, 
      "ТИМ": "КОЖУФ ГЕВГЕЛИЈА",
      "ИЗИГРАНИ": 15,
      "ПОБЕДЕНИ": 7,
      "НЕРЕШЕНИ": 2,
      "ИЗГУБЕНИ": 6,
      "ГОЛОВИДП": "25:22",
      "ГОЛРАЗЛИКА": 3,
      "ПОЕНИ": 23
    },
    {
      "ПОЗИЦИЈА": 6,
      "ТИМ": "ОХРИД",
      "ИЗИГРАНИ": 15,
      "ПОБЕДЕНИ": 7,
      "НЕРЕШЕНИ": 2,
      "ИЗГУБЕНИ": 6,
      "ГОЛОВИДП": "17:15",
      "ГОЛРАЗЛИКА": 2,
      "ПОЕНИ": 23
    },
    {
      "ПОЗИЦИЈА": 7,
      "ТИМ": "НОВАЦИ",
      "ИЗИГРАНИ": 15,
      "ПОБЕДЕНИ": 7,
      "НЕРЕШЕНИ": 1,
      "ИЗГУБЕНИ": 7,
      "ГОЛОВИДП": "19:25",
      "ГОЛРАЗЛИКА": -6,
      "ПОЕНИ": 22
    },
    {
      "ПОЗИЦИЈА": 8,  
      "ТИМ": "ФК СКОПЈЕ",
      "ИЗИГРАНИ": 15,
      "ПОБЕДЕНИ": 6,
      "НЕРЕШЕНИ": 3,
      "ИЗГУБЕНИ": 6,
      "ГОЛОВИДП": "14:18",
      "ГОЛРАЗЛИКА": -4,
      "ПОЕНИ": 21
    },
    {
      "ПОЗИЦИЈА": 9,  
      "ТИМ": "БЕЛАСИЦА",
      "ИЗИГРАНИ": 15,
      "ПОБЕДЕНИ": 6,
      "НЕРЕШЕНИ": 2,
      "ИЗГУБЕНИ": 7,
      "ГОЛОВИДП": "20:18",
      "ГОЛРАЗЛИКА": 2,
      "ПОЕНИ": 20
    },
    {
      "ПОЗИЦИЈА": 10,  
      "ТИМ": "ВАРДАР НЕГОТИНО",
      "ИЗИГРАНИ": 15,
      "ПОБЕДЕНИ": 5,
      "НЕРЕШЕНИ": 3,
      "ИЗГУБЕНИ": 7,
      "ГОЛОВИДП": "17:21",
      "ГОЛРАЗЛИКА": -4,
      "ПОЕНИ": 18
    },
    {
      "ПОЗИЦИЈА": 11,  
      "ТИМ": "ТЕТЕКС",
      "ИЗИГРАНИ": 15,
      "ПОБЕДЕНИ": 5,
      "НЕРЕШЕНИ": 3,
      "ИЗГУБЕНИ": 7,
      "ГОЛОВИДП": "17:24",
      "ГОЛРАЗЛИКА": -7,
      "ПОЕНИ": 18
    },
    {
      "ПОЗИЦИЈА": 12,  
      "ТИМ": "БАШКИМИ",
      "ИЗИГРАНИ": 15,
      "ПОБЕДЕНИ": 5,
      "НЕРЕШЕНИ": 3,
      "ИЗГУБЕНИ": 7,
      "ГОЛОВИДП": "15:30",
      "ГОЛРАЗЛИКА": -15,
      "ПОЕНИ": 18
    },
    {
      "ПОЗИЦИЈА": 13,  
      "ТИМ": "ПОБЕДА",
      "ИЗИГРАНИ": 15,
      "ПОБЕДЕНИ": 4,
      "НЕРЕШЕНИ": 3,
      "ИЗГУБЕНИ": 8,
      "ГОЛОВИДП": "18:27",
      "ГОЛРАЗЛИКА": -9,
      "ПОЕНИ": 15
    },
    {
      "ПОЗИЦИЈА": 14,  
      "ТИМ": "ОСОГОВО",
      "ИЗИГРАНИ": 15,
      "ПОБЕДЕНИ": 3,
      "НЕРЕШЕНИ": 3,
      "ИЗГУБЕНИ": 9,
      "ГОЛОВИДП": "16:29",
      "ГОЛРАЗЛИКА": -13,
      "ПОЕНИ": 12
    },
    {
      "ПОЗИЦИЈА": 15,  
      "ТИМ": "КАРАОРМАН",
      "ИЗИГРАНИ": 15,
      "ПОБЕДЕНИ": 3,
      "НЕРЕШЕНИ": 2,
      "ИЗГУБЕНИ": 10,
      "ГОЛОВИДП": "14:30",
      "ГОЛРАЗЛИКА": -16,
      "ПОЕНИ": 11
    },
    {
      "ПОЗИЦИЈА": 16,  
      "ТИМ": "КАМЕНИЦА САСА",
      "ИЗИГРАНИ": 15,
      "ПОБЕДЕНИ": 1,
      "НЕРЕШЕНИ": 5,
      "ИЗГУБЕНИ": 9,
      "ГОЛОВИДП": "16:31",
      "ГОЛРАЗЛИКА": -15,
      "ПОЕНИ": 8
    }
]
